kinto_http/__init__.py
kinto_http/batch.py
kinto_http/cli_utils.py
kinto_http/client.py
kinto_http/constants.py
kinto_http/endpoints.py
kinto_http/exceptions.py
kinto_http/login.py
kinto_http/patch_type.py
kinto_http/replication.py
kinto_http/session.py
kinto_http/utils.py
kinto_http-11.9.0.dist-info/licenses/LICENSE
kinto_http-11.9.0.dist-info/METADATA
kinto_http-11.9.0.dist-info/WHEEL
kinto_http-11.9.0.dist-info/top_level.txt
kinto_http-11.9.0.dist-info/RECORD
