Metadata-Version: 2.4
Name: kinto-http
Version: 11.9.0
Summary: Kinto client
Author-email: Mozilla Services <developers@kinto-storage.org>
License: Copyright 2012 - Mozilla Foundation
Project-URL: Repository, https://github.com/Kinto/kinto-http.py
Keywords: web services
Classifier: Programming Language :: Python
Classifier: Programming Language :: Python :: 3
Classifier: Programming Language :: Python :: Implementation :: CPython
Classifier: Topic :: Internet :: WWW/HTTP
Classifier: Topic :: Internet :: WWW/HTTP :: WSGI :: Application
Classifier: License :: OSI Approved :: Apache Software License
License-File: LICENSE
Requires-Dist: Unidecode
Requires-Dist: requests
Requires-Dist: backoff
Provides-Extra: dev
Requires-Dist: kinto; extra == "dev"
Requires-Dist: kinto-attachment; extra == "dev"
Requires-Dist: ruff; extra == "dev"
Requires-Dist: pytest; extra == "dev"
Requires-Dist: pytest-asyncio; extra == "dev"
Requires-Dist: pytest-cache; extra == "dev"
Requires-Dist: pytest-cov; extra == "dev"
Requires-Dist: pytest-mock; extra == "dev"
Requires-Dist: pytest-xdist; extra == "dev"
Dynamic: license-file
